my_package/__init__.py
my_package/module.py
my_package_kirill_panichkin-0.1.dist-info/licenses/LICENSE
my_package_kirill_panichkin-0.1.dist-info/METADATA
my_package_kirill_panichkin-0.1.dist-info/WHEEL
my_package_kirill_panichkin-0.1.dist-info/top_level.txt
my_package_kirill_panichkin-0.1.dist-info/RECORD
